stigg/__init__.py
stigg/client.py
stigg/generated/__init__.py
stigg/generated/operations.py
stigg/generated/schema.py
stigg_api_client-5.187.0.dist-info/LICENSE
stigg_api_client-5.187.0.dist-info/METADATA
stigg_api_client-5.187.0.dist-info/WHEEL
stigg_api_client-5.187.0.dist-info/RECORD
