Metadata-Version: 2.1
Name: stigg-api-client
Version: 5.187.0
Summary: 
License: STIGG SDK LICENSE
Author: Stigg
Author-email: support@stigg.io
Requires-Python: >=3.7,<4.0
Classifier: License :: Other/Proprietary License
Classifier: Programming Language :: Python :: 3
Classifier: Programming Language :: Python :: 3.7
Classifier: Programming Language :: Python :: 3.8
Classifier: Programming Language :: Python :: 3.9
Classifier: Programming Language :: Python :: 3.10
Classifier: Programming Language :: Python :: 3.11
Requires-Dist: graphql-core (>=3.1,<4.0)
Requires-Dist: requests (>=2.28,<3.0)
Requires-Dist: sgqlc (>=16.0,<17.0)
Requires-Dist: tenacity (>=8.2.2,<9.0.0)
